{"cameraMode":{"drawMode":0,"name":"Shaded","section":"Shading Mode"},"sceneLighting":true,"audioPlay":false,"sceneViewState":{"m_AlwaysRefresh":false,"showFog":true,"showSkybox":true,"showFlares":true,"showImageEffects":true,"showParticleSystems":true,"showVisualEffectGraphs":true,"m_FxEnabled":true},"in2DMode":false,"pivot":{"x":5.318496227264404,"y":-2.6262660026550295,"z":1.5057443380355836},"rotation":{"x":-0.21879597008228303,"y":-0.5364171862602234,"z":0.1464373767375946,"w":-0.8018873333930969},"size":5.6034674644470219,"orthographic":false}